forgetest/__init__.py
forgetest/cli.py
forge_test-1.1.0.dist-info/LICENSE
forge_test-1.1.0.dist-info/METADATA
forge_test-1.1.0.dist-info/WHEEL
forge_test-1.1.0.dist-info/entry_points.txt
forge_test-1.1.0.dist-info/RECORD
